pyq/kernel.py
pyq_kernel-1.2.data/data/q/pyq-kernel.p
pyq_kernel-1.2.dist-info/METADATA
pyq_kernel-1.2.dist-info/WHEEL
pyq_kernel-1.2.dist-info/top_level.txt
pyq_kernel-1.2.dist-info/RECORD
