Metadata-Version: 2.1
Name: pyq-kernel
Version: 1.2
Summary: PyQ kernel for Jupyter
Home-page: http://pyq.enlnt.com
Author: Enlightenment Research, LLC
Author-email: pyq@enlnt.com
License: UNKNOWN
Platform: UNKNOWN
Classifier: Development Status :: 4 - Beta
Classifier: Intended Audience :: Developers
Classifier: License :: OSI Approved :: BSD License
Classifier: Programming Language :: Python :: 2.7
Classifier: Programming Language :: Python :: 3
Classifier: Environment :: Web Environment
